Metadata-Version: 2.1
Name: pgserials
Version: 0.0.1
Summary: use postgresql to process time serials data
Home-page: https://github.com/ipconfiger/pgserials
Author: Alexander.Li
Author-email: superpowerlee@gmaial.com
License: UNKNOWN
Platform: UNKNOWN
License-File: LICENSE
